vending_machine.v
// The below code if for a VENDING MACHINE with only 1 product in it, the price of the product is 15Rs....

module vending_machine (clk, rst, in, out, change);

input clk, rst;
input [1:0] in; // 00: 0rs, 01: 5Rs, 10: 10Rs
output reg out;
output reg [1:0] change;

reg [1:0] c_state, n_state;

parameter S0 = 2'b00; // 0Rs
parameter S1 = 2'b01; // 5Rs
parameter S2 = 2'b10; // 10Rs

always @(posedge clk or posedge rst) begin
    if(rst) begin
        c_state <= S0;
        out <= 1'b0;
        change <= 2'b00;
    end else begin

        c_state <= n_state;
        
        case (c_state)
        S0: begin
            if (in == 2'b00) begin
                out <= 1'b0;
                change <= 2'b00;
            end else if (in == 2'b01) begin
                out <= 1'b0;
                change <= 2'b00;
            end else if (in == 2'b10) begin
                out <= 1'b0;
                change <= 2'b00;
            end
        end

        S1: begin
            if (in == 2'b00) begin
                out <= 1'b0;
                change <= 2'b01;  
            end else if (in == 2'b01) begin
                out <= 1'b0;
                change <= 2'b00;
            end else if (in == 2'b10) begin
                out <= 1'b1;      
                change <= 2'b00;
            end
        end
        
        S2: begin
            if (in == 2'b00) begin
                out <= 1'b0;
                change <= 2'b10;  
            end else if (in == 2'b01) begin
                out <= 1'b1;      
                change <= 2'b00;
            end else if (in == 2'b10) begin
                out <= 1'b1;      
                change <= 2'b01;  
            end
        end
        endcase
    end
end

always @(*) begin
    
    n_state = c_state;
    
    case (c_state)
    S0: begin
        if (in == 2'b00) begin
            n_state = S0;
        end else if (in == 2'b01) begin
            n_state = S1;
        end else if (in == 2'b10) begin
            n_state = S2;
        end
    end

    S1: begin
        if (in == 2'b00) begin
            n_state = S0;
        end else if (in == 2'b01) begin
            n_state = S2;
        end else if (in == 2'b10) begin
            n_state = S0;
        end
    end
    
    S2: begin
        if (in == 2'b00) begin
            n_state = S0;
        end else if (in == 2'b01) begin
            n_state = S0;
        end else if (in == 2'b10) begin
            n_state = S0;
        end
    end
    
    default: begin
        n_state = S0;
    end
    endcase
end

endmodule

vending_machine_tb.v
`timescale 1ns/1ns
`include "vending_machine.v"

module vending_machine_tb; 

reg clk, rst;
reg [1:0] in;
wire [1:0] change;
wire out;

vending_machine uut (clk, rst, in, out, change);

initial begin
    $dumpfile("vending_machine.vcd");
    $dumpvars(0, vending_machine_tb);

    $monitor("time: %0t || clk: %0b || rst: %0b || in: %b || out: %b || change: %b", $time, clk, rst, in, out, change);
    
    clk = 0;
    rst = 1;
    in = 2'b00;
     
    #6 rst = 0; in = 2'b01;  

    #10 in = 2'b01;          
    #10 in = 2'b01;         
    #10 in = 2'b00;          
    #10 in = 2'b10;          
    #10 in = 2'b01;          
    #10 in = 2'b10;          
    #10 in = 2'b10;          
    #20 $finish;
end

always #5 clk = ~clk;

endmodule

vending_machine.vcd
$date
	Mon Jul 14 11:51:01 2025
$end
$version
	Icarus Verilog
$end
$timescale
	1ns
$end
$scope module vending_machine_tb $end
$var wire 1 ! out $end
$var wire 2 " change [1:0] $end
$var reg 1 # clk $end
$var reg 2 $ in [1:0] $end
$var reg 1 % rst $end
$scope module uut $end
$var wire 1 # clk $end
$var wire 2 & in [1:0] $end
$var wire 1 % rst $end
$var parameter 2 ' S0 $end
$var parameter 2 ( S1 $end
$var parameter 2 ) S2 $end
$var reg 2 * c_state [1:0] $end
$var reg 2 + change [1:0] $end
$var reg 2 , n_state [1:0] $end
$var reg 1 ! out $end
$upscope $end
$upscope $end
$enddefinitions $end
$comment Show the parameter values. $end
$dumpall
b10 )
b1 (
b0 '
$end
#0
$dumpvars
b0 ,
b0 +
b0 *
b0 &
1%
b0 $
0#
b0 "
0!
$end
#5
1#
#6
b1 ,
b1 $
b1 &
0%
#10
0#
#15
b10 ,
b1 *
1#
#20
0#
#25
b0 ,
b10 *
1#
#30
0#
#35
b1 ,
1!
b0 *
1#
#36
b0 ,
b0 $
b0 &
#40
0#
#45
0!
1#
#46
b10 ,
b10 $
b10 &
#50
0#
#55
b0 ,
b10 *
1#
#56
b0 ,
b1 $
b1 &
#60
0#
#65
b1 ,
1!
b0 *
1#
#66
b10 ,
b10 $
b10 &
#70
0#
#75
b0 ,
0!
b10 *
1#
#80
0#
#85
b10 ,
b1 "
b1 +
1!
b0 *
1#
#90
0#
#95
b0 ,
b0 "
b0 +
0!
b10 *
1#
